[
  {
    "modId": "74324",
    "displayName": "Move It",
    "author": "yenyang",
    "os": "Windows",
    "installedCount": 819340,
    "translationLink": "https://crowdin.com/project/csl2-mod-move-it"
  },
  {
    "modId": "74328",
    "displayName": "529 Tiles",
    "author": "algernon",
    "os": "Windows",
    "installedCount": 388149,
    "translationLink": "https://crowdin.com/project/592-tiles"
  },
  {
    "modId": "74535",
    "displayName": "Historical Start",
    "author": "algernon",
    "os": "Windows",
    "installedCount": 19134,
    "translationLink": "https://crowdin.com/project/historical-start-cs2"
  },
  {
    "modId": "74539",
    "displayName": "Image Overlay",
    "author": "algernon",
    "os": "Windows",
    "installedCount": 32152,
    "translationLink": "https://crowdin.com/project/image-overlay"
  },
  {
    "modId": "74604",
    "displayName": "Anarchy",
    "author": "yenyang",
    "os": "Windows",
    "installedCount": 879764,
    "translationLink": "https://crowdin.com/project/csl2-mod-anarchy"
  },
  {
    "modId": "75250",
    "displayName": "Better Bulldozer",
    "author": "yenyang",
    "os": "Windows",
    "installedCount": 670881,
    "translationLink": "https://crowdin.com/project/cs2-mods-better-bulldozer"
  },
  {
    "modId": "75613",
    "displayName": "Water Features",
    "author": "yenyang",
    "os": "Windows",
    "installedCount": 372210,
    "translationLink": "https://crowdin.com/project/csl2-mod-tree-controller"
  },
  {
    "modId": "75724",
    "displayName": "ExtraLib",
    "author": "Triton Supreme",
    "os": "Windows",
    "installedCount": 725024,
    "translationLink": "https://crowdin.com/project/extralib"
  },
  {
    "modId": "75728",
    "displayName": "ExtraLandscapingTools",
    "author": "Triton Supreme",
    "os": "Windows",
    "installedCount": 396902,
    "translationLink": "https://crowdin.com/project/extralandscapingtools"
  },
  {
    "modId": "75804",
    "displayName": "Skyve",
    "author": "TDW",
    "os": "Windows",
    "installedCount": 232073,
    "translationLink": "https://crowdin.com/project/load-order-mod-2"
  },
  {
    "modId": "75816",
    "displayName": "Advanced Line Tool",
    "author": "algernon",
    "os": "Windows",
    "installedCount": 445807,
    "translationLink": "https://crowdin.com/project/line-tool-cs2"
  },
  {
    "modId": "75826",
    "displayName": "Plop the Growables",
    "author": "algernon",
    "os": "Windows",
    "installedCount": 341978,
    "translationLink": "https://crowdin.com/project/plop-the-growables"
  },
  {
    "modId": "75862",
    "displayName": "ExtendedRadio",
    "author": "Triton Supreme",
    "os": "Windows",
    "installedCount": 57925,
    "translationLink": "https://crowdin.com/project/extendedradio"
  },
  {
    "modId": "75993",
    "displayName": "Tree Controller",
    "author": "yenyang",
    "os": "Windows",
    "installedCount": 282810,
    "translationLink": "https://crowdin.com/project/csl2-mod-water-features"
  },
  {
    "modId": "77240",
    "displayName": "Find It",
    "author": "TDW",
    "os": "Windows",
    "installedCount": 578075,
    "translationLink": "https://crowdin.com/project/find-it-csii"
  },
  {
    "modId": "78960",
    "displayName": "Traffic Lights Enhancement Alpha",
    "author": "C2VMTLE",
    "os": "Windows",
    "installedCount": 208415,
    "translationLink": "https://crowdin.com/project/Cities2-TrafficLightsEnhancement"
  },
  {
    "modId": "79237",
    "displayName": "First Person Camera Continued",
    "author": "Cgameworld",
    "os": "Windows",
    "installedCount": 193226,
    "translationLink": "https://crowdin.com/project/cs2-first-person-camera-continued"
  },
  {
    "modId": "79732",
    "displayName": "[UNSTABLE] TLE Canary",
    "author": "C2VMTLE",
    "os": "Windows",
    "installedCount": 194,
    "translationLink": "https://crowdin.com/project/Cities2-TrafficLightsEnhancement"
  },
  {
    "modId": "79794",
    "displayName": "AdvancedSimulationSpeed",
    "author": "zakuro9715",
    "os": "Windows",
    "installedCount": 37171,
    "translationLink": "https://crowdin.com/project/cs2-advancedsimulationspeed"
  },
  {
    "modId": "80095",
    "displayName": "Traffic",
    "author": "krzychu124",
    "os": "Windows",
    "installedCount": 827366,
    "translationLink": "https://crowdin.com/project/traffic-cs2"
  },
  {
    "modId": "80528",
    "displayName": "ExtraDetailingTools",
    "author": "Triton Supreme",
    "os": "Windows",
    "installedCount": 397840,
    "translationLink": "https://crowdin.com/project/extradetailingtools"
  },
  {
    "modId": "80529",
    "displayName": "ExtraAssetsImporter",
    "author": "Triton Supreme",
    "os": "Windows",
    "installedCount": 466626,
    "translationLink": "https://crowdin.com/project/extraassetsimporter"
  },
  {
    "modId": "81578",
    "displayName": "SettingsManager",
    "author": "zakuro9715",
    "os": "Windows",
    "installedCount": 1393,
    "translationLink": "https://crowdin.com/project/cs2-settingsmanager"
  },
  {
    "modId": "84638",
    "displayName": "Recolor",
    "author": "yenyang",
    "os": "Windows",
    "installedCount": 186619,
    "translationLink": "https://crowdin.com/project/csl2-mod-recolor"
  },
  {
    "modId": "85284",
    "displayName": "City Stats",
    "author": "kendallroth",
    "os": "Windows",
    "installedCount": 20911,
    "translationLink": "https://crowdin.com/project/cs2-city-stats"
  },
  {
    "modId": "86124",
    "displayName": "Trading Cost Tweaker",
    "author": "StarQ",
    "os": "Windows",
    "installedCount": 2029,
    "translationLink": "https://crowdin.com/project/cities2-mods"
  },
  {
    "modId": "86260",
    "displayName": "Compass",
    "author": "Cgameworld",
    "os": "Windows",
    "installedCount": 4169,
    "translationLink": "https://crowdin.com/project/cs2-compass-mod"
  },
  {
    "modId": "87190",
    "displayName": "Road Builder [BETA]",
    "author": "TDW",
    "os": "Windows",
    "installedCount": 456877,
    "translationLink": "https://crowdin.com/project/road-builder-cs-ii"
  },
  {
    "modId": "87428",
    "displayName": "Carto",
    "author": "Taipei Native",
    "os": "Windows",
    "installedCount": 10270,
    "translationLink": "https://crowdin.com/project/carto"
  },
  {
    "modId": "88524",
    "displayName": "ON1 Portrait LUT Pack",
    "author": "Nyyoko",
    "os": "Windows",
    "installedCount": 3990,
    "translationLink": "https://crowdin.com/project/lumina"
  },
  {
    "modId": "88863",
    "displayName": "PolyHaven Cubemap Pack Pure Sky",
    "author": "Nyyoko",
    "os": "Windows",
    "installedCount": 2490,
    "translationLink": "https://crowdin.com/project/lumina"
  },
  {
    "modId": "89495",
    "displayName": "City Controller",
    "author": "Mbyron26",
    "os": "Windows",
    "installedCount": 26883,
    "translationLink": "https://crowdin.com/project/city-controller"
  },
  {
    "modId": "89556",
    "displayName": "Minecraft HDRI Sky",
    "author": "Nyyoko",
    "os": "Windows",
    "installedCount": 191,
    "translationLink": "https://crowdin.com/project/lumina"
  },
  {
    "modId": "89804",
    "displayName": "[UNSTABLE] TLE 0.3 Preview",
    "author": "C2VMTLE",
    "os": "Windows",
    "installedCount": 1387,
    "translationLink": "https://crowdin.com/project/Cities2-TrafficLightsEnhancement"
  },
  {
    "modId": "90641",
    "displayName": "Hall of Fame",
    "author": "toverux",
    "os": "Windows",
    "installedCount": 8139,
    "translationLink": "https://crowdin.com/project/halloffame-cs2"
  },
  {
    "modId": "91433",
    "displayName": "InfoLoom",
    "author": "Bruceyboy24804",
    "os": "Windows",
    "installedCount": 41699,
    "translationLink": "https://crowdin.com/project/info-loom"
  },
  {
    "modId": "92671",
    "displayName": "StarQ's Workflow Kit",
    "author": "StarQ",
    "os": "Windows",
    "installedCount": 1311,
    "translationLink": "https://crowdin.com/project/cities2-mods"
  },
  {
    "modId": "94394",
    "displayName": "Lumina",
    "author": "Nyyoko",
    "os": "Windows",
    "installedCount": 55323,
    "translationLink": "https://crowdin.com/project/lumina"
  },
  {
    "modId": "98560",
    "displayName": "Asset UI Manager",
    "author": "StarQ",
    "os": "Windows",
    "installedCount": 38963,
    "translationLink": "https://crowdin.com/project/cities2-mods"
  },
  {
    "modId": "101251",
    "displayName": "Zoning By-Law Builder [Beta]",
    "author": "Trejak",
    "os": "Windows",
    "installedCount": 4278,
    "translationLink": "https://crowdin.com/project/zoning-by-law-builder-cs2"
  },
  {
    "modId": "102147",
    "displayName": "Advanced Road Tools",
    "author": "Kemorno",
    "os": "Windows",
    "installedCount": 52796,
    "translationLink": "https://crowdin.com/project/advancedroadtools"
  },
  {
    "modId": "107257",
    "displayName": "System Clock",
    "author": "ssharp0",
    "os": "Windows",
    "installedCount": 1055,
    "translationLink": "https://crowdin.com/project/cites-skyline2-system-clock-mod"
  },
  {
    "modId": "108773",
    "displayName": "Skyve [BETA]",
    "author": "TDW",
    "os": "Windows",
    "installedCount": 21829,
    "translationLink": "https://crowdin.com/project/load-order-mod-2"
  },
  {
    "modId": "112283",
    "displayName": "Advanced Building Control",
    "author": "StarQ",
    "os": "Windows",
    "installedCount": 2949,
    "translationLink": "https://crowdin.com/project/starq-cities2"
  },
  {
    "modId": "113470",
    "displayName": "Lumina [Experimental]",
    "author": "Nyyoko",
    "os": "Windows",
    "installedCount": 477,
    "translationLink": "https://crowdin.com/project/lumina"
  },
  {
    "modId": "113708",
    "displayName": "Prefab Asset Fixes",
    "author": "StarQ",
    "os": "Windows",
    "installedCount": 10366,
    "translationLink": "https://crowdin.com/project/cities2-mods"
  },
  {
    "modId": "125278",
    "displayName": "Platter [Alpha]",
    "author": "LucaDevDesign",
    "os": "Windows",
    "installedCount": 63659,
    "translationLink": "https://crowdin.com/project/platter-cs2"
  },
  {
    "modId": "127507",
    "displayName": "Asset Migration Utility",
    "author": "StarQ",
    "os": "Windows",
    "installedCount": 4942,
    "translationLink": "https://crowdin.com/project/starq-cities2"
  },
  {
    "modId": "128911",
    "displayName": "Traffic Lights Enhancement",
    "author": "Bruceyboy24804",
    "os": "Windows",
    "installedCount": 38459,
    "translationLink": "https://crowdin.com/project/Cities2-TrafficLightsEnhancement"
  },
  {
    "modId": "129789",
    "displayName": "Topo Toggle",
    "author": "yenyang",
    "os": "Windows",
    "installedCount": 10102,
    "translationLink": "https://crowdin.com/project/csl2-mod-topo-toggle"
  },
  {
    "modId": "132866",
    "displayName": "Clearance Helper",
    "author": "LucaDevDesign",
    "os": "Windows",
    "installedCount": 883,
    "translationLink": "https://crowdin.com/project/clearance-cs2"
  }
]
